{
    "corpus_titles": {
        "dickens": "Novels by Charles Dickens",
        "ntc": "19th century reference corpus",
        "ChiLit": "Children's Literature",
        "Other": "Other"
    },
    "corpus_order": {
        "dickens": 10,
        "ntc": 20,
        "ChiLit": 30,
        "Other": 99
    },
    "book_corpus": {
        "BH": "dickens",
        "BR": "dickens",
        "DC": "dickens",
        "DS": "dickens",
        "ED": "dickens",
        "GE": "dickens",
        "HT": "dickens",
        "LD": "dickens",
        "MC": "dickens",
        "NN": "dickens",
        "OCS": "dickens",
        "OMF": "dickens",
        "OT": "dickens",
        "PP": "dickens",
        "TTC": "dickens",
        "AgnesG": "ntc",
        "Antoni": "ntc",
        "arma": "ntc",
        "cran": "ntc",
        "Deronda": "ntc",
        "dracula": "ntc",
        "emma": "ntc",
        "frank": "ntc",
        "jane": "ntc",
        "Jude": "ntc",
        "LadyAud": "ntc",
        "mary": "ntc",
        "NorthS": "ntc",
        "persuasion": "ntc",
        "pride": "ntc",
        "sybil": "ntc",
        "Tess": "ntc",
        "basker": "ntc",
        "Pomp": "ntc",
        "mill": "ntc",
        "dorian": "ntc",
        "Prof": "ntc",
        "native": "ntc",
        "alli": "ntc",
        "Jekyll": "ntc",
        "wwhite": "ntc",
        "vanity": "ntc",
        "VivianG": "ntc",
        "wh": "ntc"
    },
    "book_titles": {
        "BH": "Bleak House",
        "DC": "David Copperfield",
        "HT": "Hard Times",
        "dorian": "The Picture of Dorian Gray",
        "BR": "Barnaby Rudge",
        "Prof": "The Professor",
        "OCS": "The Old Curiosity Shop",
        "DS": "Dombey and Son",
        "Tess": "Tess of the D'Urbervilles",
        "LD": "Little Dorrit",
        "sybil": "Sybil, or the two nations",
        "NN": "Nicholas Nickleby",
        "wwhite": "The Woman in White",
        "alli": "The Small House at Allington",
        "Deronda": "Daniel Deronda",
        "Jekyll": "The Strange Case of Dr Jekyll and Mr Hyde",
        "dracula": "Dracula",
        "TTC": "A Tale of Two Cities",
        "cran": "Cranford",
        "persuasion": "Persuasion",
        "mary": "Mary Barton",
        "arma": "Armadale",
        "ED": "The Mystery of Edwin Drood",
        "Antoni": "Antonina, or the Fall of Rome",
        "PP": "Pickwick Papers",
        "Jude": "Jude the Obscure",
        "AgnesG": "Agnes Grey",
        "jane": "Jane Eyre",
        "GE": "Great Expectations",
        "VivianG": "Vivian Grey",
        "Pomp": "The Last Days of Pompeii",
        "wh": "Wuthering Heights",
        "vanity": "Vanity Fair",
        "pride": "Pride and Prejudice",
        "emma": "Emma",
        "OMF": "Our Mutual Friend",
        "MC": "Martin Chuzzlewit",
        "frank": "Frankenstein",
        "LadyAud": "Lady Audley's Secret",
        "native": "The Return of the Native",
        "NorthS": "North and South",
        "mill": "The Mill on the Floss",
        "OT": "Oliver Twist",
        "basker": "The Hound of the Baskervilles"
    },
    "book_authors": {
        "BH": "Charles Dickens",
        "DC": "Charles Dickens",
        "HT": "Charles Dickens",
        "dorian": "Oscar Wilde",
        "BR": "Charles Dickens",
        "Prof": "Charlotte Brontë",
        "OCS": "Charles Dickens",
        "DS": "Charles Dickens",
        "Tess": "Thomas Hardy",
        "LD": "Charles Dickens",
        "sybil": "Earl of Beaconsfield Benjamin Disraeli",
        "NN": "Charles Dickens",
        "wwhite": "Wilkie Collins",
        "alli": "Anthony Trollope",
        "Deronda": "George Eliot",
        "Jekyll": "Robert Louis Stevenson",
        "dracula": "Bram Stoker",
        "TTC": "Charles Dickens",
        "cran": "Elizabeth Cleghorn Gaskell",
        "persuasion": "Jane Austen",
        "mary": "Elizabeth Cleghorn Gaskell",
        "arma": "Wilkie Collins",
        "ED": "Charles Dickens",
        "Antoni": "Wilkie Collins",
        "PP": "Charles Dickens",
        "Jude": "Thomas Hardy",
        "AgnesG": "Anne Brontë",
        "jane": "Charlotte Brontë",
        "GE": "Charles Dickens",
        "VivianG": "Earl of Beaconsfield Benjamin Disraeli",
        "Pomp": "Baron Edward Bulwer Lytton Lytton",
        "wh": "Emily Brontë",
        "vanity": "William Makepeace Thackeray",
        "pride": "Jane Austen",
        "emma": "Jane Austen",
        "OMF": "Charles Dickens",
        "MC": "Charles Dickens",
        "frank": "Mary Wollstonecraft Shelley",
        "LadyAud": "M. E. Braddon",
        "native": "Thomas Hardy",
        "NorthS": "Elizabeth Cleghorn Gaskell",
        "mill": "George Eliot",
        "OT": "Charles Dickens",
        "basker": "Arthur Conan Doyle"
    },
    "end": {}
}